ada/__init__.py
ada/ada.py
ada/main.py
ada/query_calc.py
ada/query_memory.py
ada/query_processor.py
ada/query_show.py
ada/query_time.py
ada/test_script.py
ada/txt_editor.py
ada/txt_editor_copy.py
ada/data/ada.dat
ada/data/help.txt
ada_assistant-1.2.0.dist-info/METADATA
ada_assistant-1.2.0.dist-info/WHEEL
ada_assistant-1.2.0.dist-info/entry_points.txt
ada_assistant-1.2.0.dist-info/top_level.txt
ada_assistant-1.2.0.dist-info/RECORD
