Metadata-Version: 2.1
Name: ada-assistant
Version: 1.2.0
Summary: Ada: cmd helper that does lot of things
Author: yuquanshan
License: MIT
Requires-Python: >=3
Requires-Dist: pycrypto
